es_mapping_inspector/__about__.py
es_mapping_inspector/__init__.py
es_mapping_inspector/es_inspector.py
es_mapping_inspector/main.py
es_mapping_inspector/pydantic_inspector.py
es_mapping_inspector/utils.py
es_mapping_inspector-0.1.2.dist-info/METADATA
es_mapping_inspector-0.1.2.dist-info/WHEEL
es_mapping_inspector-0.1.2.dist-info/entry_points.txt
es_mapping_inspector-0.1.2.dist-info/licenses/LICENSE
es_mapping_inspector-0.1.2.dist-info/RECORD
