Metadata-Version: 2.4
Name: es-mapping-inspector
Version: 0.1.2
Summary: Validate, compare, and synchronize Pydantic model schemas with Elasticsearch mappings.
Project-URL: Homepage, https://github.com/maximekieffer/es-mapping-inspector
Project-URL: Issues, https://github.com/maximekieffer/es-mapping-inspector/issues
Author: maximekieffer
License: MIT License
License-File: LICENSE
Keywords: elasticsearch,mapping,pydantic,schema,validation
Classifier: Development Status :: 3 - Alpha
Classifier: Intended Audience :: Developers
Classifier: License :: OSI Approved :: MIT License
Classifier: Programming Language :: Python
Classifier: Programming Language :: Python :: 3
Classifier: Programming Language :: Python :: 3 :: Only
Classifier: Programming Language :: Python :: 3.9
Classifier: Programming Language :: Python :: 3.10
Classifier: Programming Language :: Python :: 3.11
Classifier: Programming Language :: Python :: 3.12
Classifier: Topic :: Software Development :: Libraries
Classifier: Topic :: Utilities
Requires-Python: >=3.9
Requires-Dist: elasticsearch<10,>=8
Requires-Dist: pydantic>=2.11.7
Requires-Dist: typer>=0.16.0
